varats_core-13.0.5-py3.11-nspkg.pth
varats/base/__init__.py
varats/base/commandline_option.py
varats/base/configuration.py
varats/base/sampling_method.py
varats/base/version_header.py
varats/experiment/__init__.py
varats/experiment/experiment_util.py
varats/experiment/trace_util.py
varats/experiment/wllvm.py
varats/experiment/workload_util.py
varats/experiment/steps/__init__.py
varats/experiment/steps/patch.py
varats/experiment/steps/recompile.py
varats/mapping/__init__.py
varats/mapping/author_map.py
varats/mapping/commit_map.py
varats/mapping/configuration_map.py
varats/paper/__init__.py
varats/paper/case_study.py
varats/paper/paper_config.py
varats/project/__init__.py
varats/project/project_domain.py
varats/project/project_util.py
varats/project/sources.py
varats/project/varats_command.py
varats/project/varats_project.py
varats/provider/__init__.py
varats/provider/provider.py
varats/provider/bug/__init__.py
varats/provider/bug/bug.py
varats/provider/bug/bug_provider.py
varats/provider/cve/__init__.py
varats/provider/cve/cve.py
varats/provider/cve/cve_map.py
varats/provider/cve/cve_provider.py
varats/provider/feature/__init__.py
varats/provider/feature/feature_model_provider.py
varats/provider/patch/__init__.py
varats/provider/patch/patch_provider.py
varats/provider/release/__init__.py
varats/provider/release/release_provider.py
varats/report/__init__.py
varats/report/gnu_time_report.py
varats/report/hot_functions_report.py
varats/report/linux_perf_report.py
varats/report/multi_patch_report.py
varats/report/report.py
varats/report/tef_report.py
varats/revision/__init__.py
varats/revision/revisions.py
varats/utils/__init__.py
varats/utils/config.py
varats/utils/exceptions.py
varats/utils/filesystem_util.py
varats/utils/git_commands.py
varats/utils/git_util.py
varats/utils/github_util.py
varats/utils/logger_util.py
varats/utils/settings.py
varats/utils/yaml_util.py
varats_core-13.0.5.dist-info/METADATA
varats_core-13.0.5.dist-info/WHEEL
varats_core-13.0.5.dist-info/namespace_packages.txt
varats_core-13.0.5.dist-info/top_level.txt
varats_core-13.0.5.dist-info/RECORD
