Metadata-Version: 2.1
Name: varats-core
Version: 13.0.5
Home-page: https://github.com/se-sic/vara-tool-suite
Author: Florian Sattler
Author-email: sattlerf@cs.uni-saarland.de
Requires-Python: >=3.9
Requires-Dist: benchbuild>=6.8
Requires-Dist: ijson>=3.1.4
Requires-Dist: plumbum>=1.6
Requires-Dist: PyGithub>=1.58
Requires-Dist: PyDriller>=2.4.1
Requires-Dist: requests>=2.28.2
Requires-Dist: packaging>=20.1
Requires-Dist: pygit2>=1.10
